{"lastUsed":1572966333683,"path":"C:\/repos\/java-instruction\/eclipse-workspace","projectCount":2,"recentFiles":[{"path":"\/PRS-Console\/src\/business","parentWorkspace":"C:\/repos\/java-instruction\/eclipse-workspace","name":"User.java","lastModified":1572888917703,"locationURI":"file:\/C:\/repos\/java-instruction\/eclipse-workspace\/PRS-Console\/src\/business\/User.java"},{"path":"\/PRS-Console\/src\/ui","parentWorkspace":"C:\/repos\/java-instruction\/eclipse-workspace","name":"UserTextFile.java","lastModified":1572888945043,"locationURI":"file:\/C:\/repos\/java-instruction\/eclipse-workspace\/PRS-Console\/src\/ui\/UserTextFile.java"},{"path":"\/PRS-Console\/src\/util","parentWorkspace":"C:\/repos\/java-instruction\/eclipse-workspace","name":"StringUtils.java","lastModified":1572895667720,"locationURI":"file:\/C:\/repos\/java-instruction\/eclipse-workspace\/PRS-Console\/src\/util\/StringUtils.java"},{"path":"\/PRS-Console\/src\/db","parentWorkspace":"C:\/repos\/java-instruction\/eclipse-workspace","name":"BaseDB.java","lastModified":1572891579649,"locationURI":"file:\/C:\/repos\/java-instruction\/eclipse-workspace\/PRS-Console\/src\/db\/BaseDB.java"},{"path":"\/hello","parentWorkspace":"C:\/repos\/java-instruction\/eclipse-workspace","name":"pom.xml","lastModified":1572931856958,"locationURI":"file:\/C:\/repos\/java-instruction\/eclipse-workspace\/hello\/pom.xml"},{"path":"\/PRS-Console\/src\/db","parentWorkspace":"C:\/repos\/java-instruction\/eclipse-workspace","name":"UserDB.java","lastModified":1572924454251,"locationURI":"file:\/C:\/repos\/java-instruction\/eclipse-workspace\/PRS-Console\/src\/db\/UserDB.java"},{"path":"\/PRS-Console\/src\/ui","parentWorkspace":"C:\/repos\/java-instruction\/eclipse-workspace","name":"PRSApp.java","lastModified":1572965868815,"locationURI":"file:\/C:\/repos\/java-instruction\/eclipse-workspace\/PRS-Console\/src\/ui\/PRSApp.java"}]}